reweight/README.md
reweight/__init__.py
reweight/data/README.md
reweight/logic/README.md
reweight/logic/__init__.py
reweight/logic/process_data.py
reweight/logic/reweight.py
reweight/tests/README.md
reweight/tests/test_installation.py
reweight/tests/test_pytorch_logic.py
reweight/tests/test_uk_prototype.py
reweight/tests/test_us_prototype.py
policyengine_reweight-0.4.0.dist-info/LICENSE
policyengine_reweight-0.4.0.dist-info/METADATA
policyengine_reweight-0.4.0.dist-info/WHEEL
policyengine_reweight-0.4.0.dist-info/top_level.txt
policyengine_reweight-0.4.0.dist-info/RECORD
